imagine_client_py/__init__.py
imagine_client_py/client.py
imagine_client_py/image_based_model.py
imagine_client_py/utils.py
tests/__init__.py
tests/test_client.py
tests/test_models.py
tests/test_utils.py
imagine_client_py-0.3.0.dist-info/LICENSE
imagine_client_py-0.3.0.dist-info/METADATA
imagine_client_py-0.3.0.dist-info/WHEEL
imagine_client_py-0.3.0.dist-info/top_level.txt
imagine_client_py-0.3.0.dist-info/RECORD
