Metadata-Version: 2.1
Name: imagine-client-py
Version: 0.3.0
Summary: A python client for doc.ai's Imagine API
Home-page: https://github.com/doc-ai/imagine-client-py.git
Author: Steven Chand
Author-email: steven@doc.ai
License: UNKNOWN
Platform: UNKNOWN
